open_tts/__init__.py
open_tts/tts.py
open_tts-2.0.0.dist-info/LICENSE
open_tts-2.0.0.dist-info/METADATA
open_tts-2.0.0.dist-info/WHEEL
open_tts-2.0.0.dist-info/top_level.txt
open_tts-2.0.0.dist-info/RECORD
