Metadata-Version: 2.1
Name: open-tts
Version: 2.0.0
Summary: A Python module for text-to-speech conversion using an open API
Home-page: https://sandeshai.in/projects/open-tts
Author: sandesh kumar
Author-email: support@sandeshai.in
Classifier: Development Status :: 3 - Alpha
Classifier: Intended Audience :: Developers
Classifier: License :: OSI Approved :: MIT License
Classifier: Operating System :: OS Independent
Classifier: Programming Language :: Python :: 3
Classifier: Programming Language :: Python :: 3.6
Classifier: Programming Language :: Python :: 3.7
Classifier: Programming Language :: Python :: 3.8
Classifier: Programming Language :: Python :: 3.9
Classifier: Programming Language :: Python :: 3.10
Classifier: Programming Language :: Python :: 3.11
Requires-Python: >=3.6
License-File: LICENSE
Requires-Dist: requests
Requires-Dist: playsound
Requires-Dist: colorama
Requires-Dist: beautifulsoup4
